Metadata-Version: 2.1
Name: conda-vendor
Version: 1.0.4
Summary: UNKNOWN
Home-page: https://github.com/MetroStar/conda-vendor
License: UNKNOWN
Platform: UNKNOWN
Requires-Python: >=3.6
License-File: LICENSE
